TSRCNN/__init__.py
TSRCNN/main.py
TSRCNN/deeptextures/__init__.py
TSRCNN/deeptextures/utilsFolder/__init__.py
TSRCNN/deeptextures/utilsFolder/loss.py
TSRCNN/deeptextures/utilsFolder/models.py
TSRCNN/deeptextures/utilsFolder/utils.py
TSRCNN/generatetextures/__init__.py
TSRCNN/generatetextures/main.py
TSRCNN/generatetextures/utils/__init__.py
TSRCNN/generatetextures/utils/generate.py
TSRCNN-0.0.11.dist-info/METADATA
TSRCNN-0.0.11.dist-info/WHEEL
TSRCNN-0.0.11.dist-info/top_level.txt
TSRCNN-0.0.11.dist-info/RECORD
