Metadata-Version: 2.1
Name: TSRCNN
Version: 0.0.11
Summary: TSRCNN_Texture Synthesis with Rotation using CNN package
Home-page: https://github.com/Ch00cy/TSRCNN_library
Author: Yeonhee Choo
Author-email: chooyeonhee99@gmail.com
Classifier: Programming Language :: Python :: 3
Classifier: License :: OSI Approved :: MIT License
Classifier: Operating System :: OS Independent
Requires-Python: >=3.8
